README.rst
setup.py
django_bitid.egg-info/PKG-INFO
django_bitid.egg-info/SOURCES.txt
django_bitid.egg-info/dependency_links.txt
django_bitid.egg-info/not-zip-safe
django_bitid.egg-info/requires.txt
django_bitid.egg-info/top_level.txt
djbitid/__init__.py
djbitid/admin.py
djbitid/backends.py
djbitid/client.py
djbitid/forms.py
djbitid/models.py
djbitid/tests.py
djbitid/urls.py
djbitid/views.py
djbitid/templates/djbitid/callback.html
djbitid/templates/djbitid/challenge.html