Metadata-Version: 1.1
Name: django-bitid
Version: 0.1
Summary: App for django bitId authentication
Home-page: http://github.com/manuelzs/django-bitid/
Author: Manuel Zapata
Author-email: manuelzs@gmail.com
License: UNKNOWN
Platform: UNKNOWN
Classifier: Development Status :: 4 - Beta
Classifier: Environment :: Web Environment
Classifier: Framework :: Django
Classifier: Intended Audience :: Developers
Classifier: License :: OSI Approved :: MIT License
Classifier: Operating System :: OS Independent
Classifier: Programming Language :: Python
Requires: south(>=0.8.4)
Requires: pytz(>=2014.3)
